{
  "meta": {
    "version": 1,
    "request": "http://nba.cloud/league/00/2025/02/09/scoreboard?Format=json",
    "time": "2025-03-26T13:15:08.158Z"
  },
  "scoreboard": {
    "gameDate": "2025-02-09",
    "leagueId": "00",
    "leagueName": "National Basketball Association",
    "games": [
      {
        "gameId": "0022400752",
        "gameCode": "20250209/CHADET",
        "gameStatus": 3,
        "gameStatusText": "Final",
        "period": 4,
        "gameClock": "",
        "gameTimeUTC": "2025-02-09T18:00:00Z",
        "gameEt": "2025-02-09T13:00:00Z",
        "regulationPeriods": 4,
        "seriesGameNumber": "",
        "gameLabel": "",
        "gameSubLabel": "",
        "seriesText": "",
        "ifNecessary": false,
        "seriesConference": "",
        "poRoundDesc": "",
        "gameSubtype": "",
        "isNeutral": false,
        "gameLeaders": {
          "homeLeaders": {
            "personId": 1630595,
            "name": "Cade Cunningham",
            "playerSlug": "cade-cunningham",
            "jerseyNum": "2",
            "position": "G",
            "teamTricode": "DET",
            "points": 19,
            "rebounds": 10,
            "assists": 12
          },
          "awayLeaders": {
            "personId": 1628970,
            "name": "Miles Bridges",
            "playerSlug": "miles-bridges",
            "jerseyNum": "0",
            "position": "F",
            "teamTricode": "CHA",
            "points": 30,
            "rebounds": 9,
            "assists": 3
          }
        },
        "teamLeaders": {
          "homeLeaders": {
            "personId": 1630595,
            "name": "Cade Cunningham",
            "playerSlug": "cade-cunningham",
            "jerseyNum": "2",
            "position": "G",
            "teamTricode": "DET",
            "points": 25.7,
            "rebounds": 6.1,
            "assists": 9.2
          },
          "awayLeaders": {
            "personId": 1628970,
            "name": "Miles Bridges",
            "playerSlug": "miles-bridges",
            "jerseyNum": "0",
            "position": "F",
            "teamTricode": "CHA",
            "points": 20.7,
            "rebounds": 7.8,
            "assists": 3.9
          },
          "seasonLeadersFlag": 0
        },
        "broadcasters": {
          "nationalBroadcasters": [],
          "nationalRadioBroadcasters": [
            {
              "broadcasterId": 1001098,
              "broadcastDisplay": "SiriusXM",
              "broadcasterTeamId": -1,
              "broadcasterDescription": ""
            }
          ],
          "nationalOttBroadcasters": [],
          "homeTvBroadcasters": [
            {
              "broadcasterId": 1001235,
              "broadcastDisplay": "FDSNDT",
              "broadcasterTeamId": 1610612765,
              "broadcasterDescription": ""
            }
          ],
          "homeRadioBroadcasters": [
            {
              "broadcasterId": 1188,
              "broadcastDisplay": "WXYT",
              "broadcasterTeamId": 1610612765,
              "broadcasterDescription": ""
            }
          ],
          "homeOttBroadcasters": [],
          "awayTvBroadcasters": [
            {
              "broadcasterId": 1001231,
              "broadcastDisplay": "FDSNSE-CHA",
              "broadcasterTeamId": 1610612766,
              "broadcasterDescription": ""
            }
          ],
          "awayRadioBroadcasters": [
            {
              "broadcasterId": 1000862,
              "broadcastDisplay": "WFNZ-FM",
              "broadcasterTeamId": 1610612766,
              "broadcasterDescription": ""
            }
          ],
          "awayOttBroadcasters": []
        },
        "homeTeam": {
          "teamId": 1610612765,
          "teamName": "Pistons",
          "teamCity": "Detroit",
          "teamTricode": "DET",
          "teamSlug": "pistons",
          "wins": 27,
          "losses": 26,
          "score": 112,
          "seed": 0,
          "inBonus": null,
          "timeoutsRemaining": 1,
          "periods": [
            {
              "period": 1,
              "periodType": "REGULAR",
              "score": 39
            },
            {
              "period": 2,
              "periodType": "REGULAR",
              "score": 27
            },
            {
              "period": 3,
              "periodType": "REGULAR",
              "score": 24
            },
            {
              "period": 4,
              "periodType": "REGULAR",
              "score": 22
            }
          ]
        },
        "awayTeam": {
          "teamId": 1610612766,
          "teamName": "Hornets",
          "teamCity": "Charlotte",
          "teamTricode": "CHA",
          "teamSlug": "hornets",
          "wins": 13,
          "losses": 37,
          "score": 102,
          "seed": 0,
          "inBonus": null,
          "timeoutsRemaining": 0,
          "periods": [
            {
              "period": 1,
              "periodType": "REGULAR",
              "score": 15
            },
            {
              "period": 2,
              "periodType": "REGULAR",
              "score": 31
            },
            {
              "period": 3,
              "periodType": "REGULAR",
              "score": 27
            },
            {
              "period": 4,
              "periodType": "REGULAR",
              "score": 29
            }
          ]
        }
      },
      {
        "gameId": "0022400753",
        "gameCode": "20250209/TORHOU",
        "gameStatus": 3,
        "gameStatusText": "Final",
        "period": 4,
        "gameClock": "",
        "gameTimeUTC": "2025-02-09T19:00:00Z",
        "gameEt": "2025-02-09T14:00:00Z",
        "regulationPeriods": 4,
        "seriesGameNumber": "",
        "gameLabel": "",
        "gameSubLabel": "",
        "seriesText": "",
        "ifNecessary": false,
        "seriesConference": "",
        "poRoundDesc": "",
        "gameSubtype": "",
        "isNeutral": false,
        "gameLeaders": {
          "homeLeaders": {
            "personId": 1630224,
            "name": "Jalen Green",
            "playerSlug": "jalen-green",
            "jerseyNum": "4",
            "position": "G",
            "teamTricode": "HOU",
            "points": 18,
            "rebounds": 9,
            "assists": 3
          },
          "awayLeaders": {
            "personId": 1630567,
            "name": "Scottie Barnes",
            "playerSlug": "scottie-barnes",
            "jerseyNum": "4",
            "position": "F-G",
            "teamTricode": "TOR",
            "points": 15,
            "rebounds": 9,
            "assists": 7
          }
        },
        "teamLeaders": {
          "homeLeaders": {
            "personId": 1630578,
            "name": "Alperen Sengun",
            "playerSlug": "alperen-sengun",
            "jerseyNum": "28",
            "position": "C",
            "teamTricode": "HOU",
            "points": 19.0,
            "rebounds": 10.5,
            "assists": 4.9
          },
          "awayLeaders": {
            "personId": 1629628,
            "name": "RJ Barrett",
            "playerSlug": "rj-barrett",
            "jerseyNum": "9",
            "position": "F-G",
            "teamTricode": "TOR",
            "points": 21.4,
            "rebounds": 6.5,
            "assists": 5.6
          },
          "seasonLeadersFlag": 0
        },
        "broadcasters": {
          "nationalBroadcasters": [],
          "nationalRadioBroadcasters": [
            {
              "broadcasterId": 1001098,
              "broadcastDisplay": "SiriusXM",
              "broadcasterTeamId": -1,
              "broadcasterDescription": ""
            }
          ],
          "nationalOttBroadcasters": [],
          "homeTvBroadcasters": [
            {
              "broadcasterId": 1001056,
              "broadcastDisplay": "SCHN",
              "broadcasterTeamId": 1610612745,
              "broadcasterDescription": ""
            }
          ],
          "homeRadioBroadcasters": [
            {
              "broadcasterId": 1000699,
              "broadcastDisplay": "KBME/KQBU-FM",
              "broadcasterTeamId": 1610612745,
              "broadcasterDescription": ""
            }
          ],
          "homeOttBroadcasters": [],
          "awayTvBroadcasters": [
            {
              "broadcasterId": 11,
              "broadcastDisplay": "TSN",
              "broadcasterTeamId": 1610612761,
              "broadcasterDescription": ""
            }
          ],
          "awayRadioBroadcasters": [
            {
              "broadcasterId": 1494,
              "broadcastDisplay": "CHUM",
              "broadcasterTeamId": 1610612761,
              "broadcasterDescription": ""
            }
          ],
          "awayOttBroadcasters": []
        },
        "homeTeam": {
          "teamId": 1610612745,
          "teamName": "Rockets",
          "teamCity": "Houston",
          "teamTricode": "HOU",
          "teamSlug": "rockets",
          "wins": 33,
          "losses": 20,
          "score": 94,
          "seed": 0,
          "inBonus": null,
          "timeoutsRemaining": 1,
          "periods": [
            {
              "period": 1,
              "periodType": "REGULAR",
              "score": 18
            },
            {
              "period": 2,
              "periodType": "REGULAR",
              "score": 19
            },
            {
              "period": 3,
              "periodType": "REGULAR",
              "score": 21
            },
            {
              "period": 4,
              "periodType": "REGULAR",
              "score": 36
            }
          ]
        },
        "awayTeam": {
          "teamId": 1610612761,
          "teamName": "Raptors",
          "teamCity": "Toronto",
          "teamTricode": "TOR",
          "teamSlug": "raptors",
          "wins": 16,
          "losses": 37,
          "score": 87,
          "seed": 0,
          "inBonus": null,
          "timeoutsRemaining": 0,
          "periods": [
            {
              "period": 1,
              "periodType": "REGULAR",
              "score": 22
            },
            {
              "period": 2,
              "periodType": "REGULAR",
              "score": 20
            },
            {
              "period": 3,
              "periodType": "REGULAR",
              "score": 21
            },
            {
              "period": 4,
              "periodType": "REGULAR",
              "score": 24
            }
          ]
        }
      },
      {
        "gameId": "0022400754",
        "gameCode": "20250209/PHIMIL",
        "gameStatus": 3,
        "gameStatusText": "Final",
        "period": 4,
        "gameClock": "",
        "gameTimeUTC": "2025-02-09T19:00:00Z",
        "gameEt": "2025-02-09T14:00:00Z",
        "regulationPeriods": 4,
        "seriesGameNumber": "",
        "gameLabel": "",
        "gameSubLabel": "",
        "seriesText": "",
        "ifNecessary": false,
        "seriesConference": "",
        "poRoundDesc": "",
        "gameSubtype": "",
        "isNeutral": false,
        "gameLeaders": {
          "homeLeaders": {
            "personId": 203081,
            "name": "Damian Lillard",
            "playerSlug": "damian-lillard",
            "jerseyNum": "0",
            "position": "G",
            "teamTricode": "MIL",
            "points": 43,
            "rebounds": 7,
            "assists": 8
          },
          "awayLeaders": {
            "personId": 1630178,
            "name": "Tyrese Maxey",
            "playerSlug": "tyrese-maxey",
            "jerseyNum": "0",
            "position": "G",
            "teamTricode": "PHI",
            "points": 39,
            "rebounds": 4,
            "assists": 5
          }
        },
        "teamLeaders": {
          "homeLeaders": {
            "personId": 203507,
            "name": "Giannis Antetokounmpo",
            "playerSlug": "giannis-antetokounmpo",
            "jerseyNum": "34",
            "position": "F",
            "teamTricode": "MIL",
            "points": 30.2,
            "rebounds": 12.0,
            "assists": 5.9
          },
          "awayLeaders": {
            "personId": 1630178,
            "name": "Tyrese Maxey",
            "playerSlug": "tyrese-maxey",
            "jerseyNum": "0",
            "position": "G",
            "teamTricode": "PHI",
            "points": 26.3,
            "rebounds": 3.3,
            "assists": 6.1
          },
          "seasonLeadersFlag": 0
        },
        "broadcasters": {
          "nationalBroadcasters": [
            {
              "broadcasterId": 1001318,
              "broadcastDisplay": "ABC/ESPN+",
              "broadcasterTeamId": -1,
              "broadcasterDescription": ""
            }
          ],
          "nationalRadioBroadcasters": [
            {
              "broadcasterId": 3,
              "broadcastDisplay": "ESPNR",
              "broadcasterTeamId": -1,
              "broadcasterDescription": ""
            },
            {
              "broadcasterId": 1001098,
              "broadcastDisplay": "SiriusXM",
              "broadcasterTeamId": -1,
              "broadcasterDescription": ""
            }
          ],
          "nationalOttBroadcasters": [],
          "homeTvBroadcasters": [],
          "homeRadioBroadcasters": [
            {
              "broadcasterId": 1697,
              "broadcastDisplay": "WTMJ-AM/FM",
              "broadcasterTeamId": 1610612749,
              "broadcasterDescription": ""
            }
          ],
          "homeOttBroadcasters": [],
          "awayTvBroadcasters": [],
          "awayRadioBroadcasters": [
            {
              "broadcasterId": 1001343,
              "broadcastDisplay": "WMGK",
              "broadcasterTeamId": 1610612755,
              "broadcasterDescription": ""
            }
          ],
          "awayOttBroadcasters": []
        },
        "homeTeam": {
          "teamId": 1610612749,
          "teamName": "Bucks",
          "teamCity": "Milwaukee",
          "teamTricode": "MIL",
          "teamSlug": "bucks",
          "wins": 28,
          "losses": 23,
          "score": 135,
          "seed": 0,
          "inBonus": null,
          "timeoutsRemaining": 0,
          "periods": [
            {
              "period": 1,
              "periodType": "REGULAR",
              "score": 40
            },
            {
              "period": 2,
              "periodType": "REGULAR",
              "score": 25
            },
            {
              "period": 3,
              "periodType": "REGULAR",
              "score": 38
            },
            {
              "period": 4,
              "periodType": "REGULAR",
              "score": 32
            }
          ]
        },
        "awayTeam": {
          "teamId": 1610612755,
          "teamName": "76ers",
          "teamCity": "Philadelphia",
          "teamTricode": "PHI",
          "teamSlug": "sixers",
          "wins": 20,
          "losses": 32,
          "score": 127,
          "seed": 0,
          "inBonus": null,
          "timeoutsRemaining": 1,
          "periods": [
            {
              "period": 1,
              "periodType": "REGULAR",
              "score": 39
            },
            {
              "period": 2,
              "periodType": "REGULAR",
              "score": 24
            },
            {
              "period": 3,
              "periodType": "REGULAR",
              "score": 28
            },
            {
              "period": 4,
              "periodType": "REGULAR",
              "score": 36
            }
          ]
        }
      }
    ]
  }
}